<?xml version="1.0" encoding="UTF-8"?>
<response>
  <states>
    <state>
      <id>1</id>
      <name>Afghanistan</name>
      <code>AF</code>
    </state>
    <state>
      <id>2</id>
      <name>Netherlands</name>
      <code>NL</code>
    </state>
    <state>
      <id>3</id>
      <name>Netherlands Antilles</name>
      <code>AN</code>
    </state>
    <state>
      <id>4</id>
      <name>Albania</name>
      <code>AL</code>
    </state>
    <state>
      <id>5</id>
      <name>Algeria</name>
      <code>DZ</code>
    </state>
    <state>
      <id>6</id>
      <name>American Samoa</name>
      <code>AS</code>
    </state>
    <state>
      <id>7</id>
      <name>Andorra</name>
      <code>AD</code>
    </state>
    <state>
      <id>8</id>
      <name>Angola</name>
      <code>AO</code>
    </state>
    <state>
      <id>9</id>
      <name>Anguilla</name>
      <code>AI</code>
    </state>
    <state>
      <id>10</id>
      <name>Antigua and Barbuda</name>
      <code>AG</code>
    </state>
    <state>
      <id>11</id>
      <name>United Arab Emirates</name>
      <code>AE</code>
    </state>
    <state>
      <id>12</id>
      <name>Argentina</name>
      <code>AR</code>
    </state>
    <state>
      <id>13</id>
      <name>Armenia</name>
      <code>AM</code>
    </state>
    <state>
      <id>14</id>
      <name>Aruba</name>
      <code>AW</code>
    </state>
    <state>
      <id>15</id>
      <name>Australia</name>
      <code>AU</code>
    </state>
    <state>
      <id>16</id>
      <name>Azerbaijan</name>
      <code>AZ</code>
    </state>
    <state>
      <id>17</id>
      <name>Bahamas</name>
      <code>BS</code>
    </state>
    <state>
      <id>18</id>
      <name>Bahrain</name>
      <code>BH</code>
    </state>
    <state>
      <id>19</id>
      <name>Bangladesh</name>
      <code>BD</code>
    </state>
    <state>
      <id>20</id>
      <name>Barbados</name>
      <code>BB</code>
    </state>
  </states>
  <counts>
    <this>20</this>
    <total>248</total>
  </counts>
</response>
